.hgignore
LICENSE
setup.py
LDB_Setuptools_Coverage.egg-info/PKG-INFO
LDB_Setuptools_Coverage.egg-info/SOURCES.txt
LDB_Setuptools_Coverage.egg-info/dependency_links.txt
LDB_Setuptools_Coverage.egg-info/entry_points.txt
LDB_Setuptools_Coverage.egg-info/namespace_packages.txt
LDB_Setuptools_Coverage.egg-info/requires.txt
LDB_Setuptools_Coverage.egg-info/top_level.txt
ldb/__init__.py
ldb/setuptools/__init__.py
ldb/setuptools/coverage.py
test/__init__.py
test/tests.py
test_packages/test_fail_coverage/setup.py
test_packages/test_fail_coverage/my_pkg/__init__.py
test_packages/test_fail_coverage/my_pkg/mod.py
test_packages/test_fail_coverage/test/__init__.py
test_packages/test_fail_coverage/test/test.py
test_packages/test_fail_test/setup.py
test_packages/test_fail_test/my_pkg/__init__.py
test_packages/test_fail_test/my_pkg/mod.py
test_packages/test_fail_test/test/__init__.py
test_packages/test_fail_test/test/test.py
test_packages/test_pass/setup.py
test_packages/test_pass/my_pkg/__init__.py
test_packages/test_pass/my_pkg/mod.py
test_packages/test_pass/ns_pkg/__init__.py
test_packages/test_pass/ns_pkg/pkg/__init__.py
test_packages/test_pass/ns_pkg/pkg/mod.py
test_packages/test_pass/test/__init__.py
test_packages/test_pass/test/test.py