Metadata-Version: 1.1
Name: LDB-Setuptools-Coverage
Version: 0.3
Summary: Package to add coverage command to setuptools
Home-page: http://www.eldebe.org/ldb/setuptools/coverage/
Author: Alex Orange
Author-email: alex@eldebe.org
License: AGPLv3
Platform: UNKNOWN
Classifier: Development Status :: 4 - Beta
Classifier: Framework :: Setuptools Plugin
Classifier: Intended Audience :: Developers
Classifier: License :: OSI Approved :: GNU Affero General Public License v3
Classifier: Programming Language :: Python :: 2.7
Classifier: Programming Language :: Python :: 3.5
Classifier: Programming Language :: Python :: Implementation :: CPython
Classifier: Programming Language :: Python :: Implementation :: PyPy
Classifier: Topic :: Software Development :: Testing
